dlite.py
dlite-0.1.1.dist-info/LICENSE.md
dlite-0.1.1.dist-info/METADATA
dlite-0.1.1.dist-info/WHEEL
dlite-0.1.1.dist-info/top_level.txt
dlite-0.1.1.dist-info/RECORD
